svfmt_pkg/__init__.py
svfmt_pkg/svfmt_module.py
svfmt_pkg/wrapperizer.py
svfmt_pkg-0.0.1.dist-info/METADATA
svfmt_pkg-0.0.1.dist-info/WHEEL
svfmt_pkg-0.0.1.dist-info/entry_points.txt
svfmt_pkg-0.0.1.dist-info/top_level.txt
svfmt_pkg-0.0.1.dist-info/RECORD
