Metadata-Version: 2.4
Name: svfmt_pkg
Version: 0.0.1
Summary: SystemVerilog formatter/wrapper generator
Author-email: Your Name <you@example.com>
License: MIT
Requires-Python: >=3.8
